[
    {
        "name": "Emily",
        "sex": "F",
        "frequency": 25959
    },
    {
        "name": "Hannah",
        "sex": "F",
        "frequency": 23087
    },
    {
        "name": "Madison",
        "sex": "F",
        "frequency": 19968
    },
    {
        "name": "Ashley",
        "sex": "F",
        "frequency": 18000
    },
    {
        "name": "Sarah",
        "sex": "F",
        "frequency": 17715
    },
    {
        "name": "Alexis",
        "sex": "F",
        "frequency": 17631
    },
    {
        "name": "Samantha",
        "sex": "F",
        "frequency": 17264
    },
    {
        "name": "Jessica",
        "sex": "F",
        "frequency": 15711
    },
    {
        "name": "Elizabeth",
        "sex": "F",
        "frequency": 15117
    },
    {
        "name": "Taylor",
        "sex": "F",
        "frequency": 15080
    },
    {
        "name": "Lauren",
        "sex": "F",
        "frequency": 14176
    },
    {
        "name": "Alyssa",
        "sex": "F",
        "frequency": 13553
    },
    {
        "name": "Kayla",
        "sex": "F",
        "frequency": 13313
    },
    {
        "name": "Abigail",
        "sex": "F",
        "frequency": 13094
    },
    {
        "name": "Brianna",
        "sex": "F",
        "frequency": 12880
    },
    {
        "name": "Olivia",
        "sex": "F",
        "frequency": 12855
    },
    {
        "name": "Emma",
        "sex": "F",
        "frequency": 12560
    },
    {
        "name": "Megan",
        "sex": "F",
        "frequency": 11436
    },
    {
        "name": "Grace",
        "sex": "F",
        "frequency": 11284
    },
    {
        "name": "Victoria",
        "sex": "F",
        "frequency": 10926
    },
    {
        "name": "Rachel",
        "sex": "F",
        "frequency": 10687
    },
    {
        "name": "Anna",
        "sex": "F",
        "frequency": 10613
    },
    {
        "name": "Sydney",
        "sex": "F",
        "frequency": 10243
    },
    {
        "name": "Destiny",
        "sex": "F",
        "frequency": 9850
    },
    {
        "name": "Morgan",
        "sex": "F",
        "frequency": 9502
    },
    {
        "name": "Jennifer",
        "sex": "F",
        "frequency": 9390
    },
    {
        "name": "Jasmine",
        "sex": "F",
        "frequency": 9099
    },
    {
        "name": "Haley",
        "sex": "F",
        "frequency": 9069
    },
    {
        "name": "Julia",
        "sex": "F",
        "frequency": 8768
    },
    {
        "name": "Kaitlyn",
        "sex": "F",
        "frequency": 8759
    },
    {
        "name": "Nicole",
        "sex": "F",
        "frequency": 8562
    },
    {
        "name": "Amanda",
        "sex": "F",
        "frequency": 8558
    },
    {
        "name": "Katherine",
        "sex": "F",
        "frequency": 8109
    },
    {
        "name": "Natalie",
        "sex": "F",
        "frequency": 8096
    },
    {
        "name": "Hailey",
        "sex": "F",
        "frequency": 7829
    },
    {
        "name": "Alexandra",
        "sex": "F",
        "frequency": 7550
    },
    {
        "name": "Savannah",
        "sex": "F",
        "frequency": 7101
    },
    {
        "name": "Chloe",
        "sex": "F",
        "frequency": 7094
    },
    {
        "name": "Rebecca",
        "sex": "F",
        "frequency": 7078
    },
    {
        "name": "Stephanie",
        "sex": "F",
        "frequency": 7028
    },
    {
        "name": "Maria",
        "sex": "F",
        "frequency": 6856
    },
    {
        "name": "Sophia",
        "sex": "F",
        "frequency": 6564
    },
    {
        "name": "Mackenzie",
        "sex": "F",
        "frequency": 6349
    },
    {
        "name": "Allison",
        "sex": "F",
        "frequency": 6315
    },
    {
        "name": "Isabella",
        "sex": "F",
        "frequency": 6242
    },
    {
        "name": "Mary",
        "sex": "F",
        "frequency": 6221
    },
    {
        "name": "Amber",
        "sex": "F",
        "frequency": 6181
    },
    {
        "name": "Danielle",
        "sex": "F",
        "frequency": 6091
    },
    {
        "name": "Gabrielle",
        "sex": "F",
        "frequency": 5871
    },
    {
        "name": "Jordan",
        "sex": "F",
        "frequency": 5809
    },
    {
        "name": "Jacob",
        "sex": "M",
        "frequency": 34491
    },
    {
        "name": "Michael",
        "sex": "M",
        "frequency": 32043
    },
    {
        "name": "Matthew",
        "sex": "M",
        "frequency": 28580
    },
    {
        "name": "Joshua",
        "sex": "M",
        "frequency": 27542
    },
    {
        "name": "Christopher",
        "sex": "M",
        "frequency": 24937
    },
    {
        "name": "Nicholas",
        "sex": "M",
        "frequency": 24654
    },
    {
        "name": "Andrew",
        "sex": "M",
        "frequency": 23657
    },
    {
        "name": "Joseph",
        "sex": "M",
        "frequency": 22843
    },
    {
        "name": "Daniel",
        "sex": "M",
        "frequency": 22337
    },
    {
        "name": "Tyler",
        "sex": "M",
        "frequency": 21506
    },
    {
        "name": "William",
        "sex": "M",
        "frequency": 20669
    },
    {
        "name": "Brandon",
        "sex": "M",
        "frequency": 20337
    },
    {
        "name": "Ryan",
        "sex": "M",
        "frequency": 20269
    },
    {
        "name": "John",
        "sex": "M",
        "frequency": 20113
    },
    {
        "name": "Zachary",
        "sex": "M",
        "frequency": 19852
    },
    {
        "name": "David",
        "sex": "M",
        "frequency": 19787
    },
    {
        "name": "Anthony",
        "sex": "M",
        "frequency": 19655
    },
    {
        "name": "James",
        "sex": "M",
        "frequency": 17991
    },
    {
        "name": "Justin",
        "sex": "M",
        "frequency": 17783
    },
    {
        "name": "Alexander",
        "sex": "M",
        "frequency": 17290
    },
    {
        "name": "Jonathan",
        "sex": "M",
        "frequency": 16888
    },
    {
        "name": "Christian",
        "sex": "M",
        "frequency": 16057
    },
    {
        "name": "Austin",
        "sex": "M",
        "frequency": 15946
    },
    {
        "name": "Dylan",
        "sex": "M",
        "frequency": 15405
    },
    {
        "name": "Ethan",
        "sex": "M",
        "frequency": 15225
    },
    {
        "name": "Benjamin",
        "sex": "M",
        "frequency": 14844
    },
    {
        "name": "Noah",
        "sex": "M",
        "frequency": 14282
    },
    {
        "name": "Samuel",
        "sex": "M",
        "frequency": 14187
    },
    {
        "name": "Robert",
        "sex": "M",
        "frequency": 13739
    },
    {
        "name": "Nathan",
        "sex": "M",
        "frequency": 13039
    },
    {
        "name": "Cameron",
        "sex": "M",
        "frequency": 12765
    },
    {
        "name": "Kevin",
        "sex": "M",
        "frequency": 12673
    },
    {
        "name": "Thomas",
        "sex": "M",
        "frequency": 12639
    },
    {
        "name": "Jose",
        "sex": "M",
        "frequency": 12585
    },
    {
        "name": "Hunter",
        "sex": "M",
        "frequency": 12538
    },
    {
        "name": "Jordan",
        "sex": "M",
        "frequency": 12168
    },
    {
        "name": "Kyle",
        "sex": "M",
        "frequency": 11969
    },
    {
        "name": "Caleb",
        "sex": "M",
        "frequency": 9866
    },
    {
        "name": "Jason",
        "sex": "M",
        "frequency": 9778
    },
    {
        "name": "Logan",
        "sex": "M",
        "frequency": 9737
    },
    {
        "name": "Aaron",
        "sex": "M",
        "frequency": 9561
    },
    {
        "name": "Eric",
        "sex": "M",
        "frequency": 9161
    },
    {
        "name": "Brian",
        "sex": "M",
        "frequency": 8957
    },
    {
        "name": "Gabriel",
        "sex": "M",
        "frequency": 8681
    },
    {
        "name": "Adam",
        "sex": "M",
        "frequency": 8137
    },
    {
        "name": "Jack",
        "sex": "M",
        "frequency": 8123
    },
    {
        "name": "Isaiah",
        "sex": "M",
        "frequency": 8029
    },
    {
        "name": "Juan",
        "sex": "M",
        "frequency": 7711
    },
    {
        "name": "Luis",
        "sex": "M",
        "frequency": 7662
    },
    {
        "name": "Connor",
        "sex": "M",
        "frequency": 7529
    }
]
   